CHANGES.md
LICENSE
MANIFEST.in
README.md
setup.cfg
setup.py
tox.ini
LstGen.egg-info/PKG-INFO
LstGen.egg-info/SOURCES.txt
LstGen.egg-info/dependency_links.txt
LstGen.egg-info/entry_points.txt
LstGen.egg-info/not-zip-safe
LstGen.egg-info/requires.txt
LstGen.egg-info/top_level.txt
lstgen/__init__.py
lstgen/cli.py
lstgen/pap.py
lstgen/generators/__init__.py
lstgen/generators/ast2code.py
lstgen/generators/base.py
lstgen/generators/java.py
lstgen/generators/javascript.py
lstgen/generators/golang/BigDecimal.go
lstgen/generators/golang/__init__.py
lstgen/generators/php/BigDecimal.php
lstgen/generators/php/__init__.py
lstgen/generators/python/__init__.py
lstgen/generators/python/bd.py