Metadata-Version: 2.1
Name: LstGen
Version: 0.6.5
Summary: LstGen
Home-page: http://github.com/jenner/LstGen
Author: Igor Stroh
Author-email: igor.stroh@rulim.de
License: UNKNOWN
Keywords: lohnsteuer code generator cli
Platform: UNKNOWN
Classifier: Programming Language :: Python
Classifier: Programming Language :: Python :: 2.7
Classifier: Programming Language :: Python :: 3.4
Classifier: Programming Language :: Python :: 3.5
Classifier: Programming Language :: Python :: 3.6
Classifier: Programming Language :: Python :: 3.7
Classifier: Programming Language :: Python :: 3.8
Classifier: Topic :: Software Development :: Code Generators
Provides-Extra: testing
License-File: LICENSE
